setup.py
tushare_hqchart/__init__.py
tushare_hqchart/hqchartpy2_tushare.py
tushare_hqchart/pkg_info.json
tushare_hqchart.egg-info/PKG-INFO
tushare_hqchart.egg-info/SOURCES.txt
tushare_hqchart.egg-info/dependency_links.txt
tushare_hqchart.egg-info/requires.txt
tushare_hqchart.egg-info/top_level.txt