Metadata-Version: 1.1
Name: tushare-hqchart
Version: 1.0.1
Summary: HQChartPy2 C++
Home-page: https://github.com/jones2000/HQChart
Author: jones2000
Author-email: jones_2000@163.com
License: Apache License 2.0
Keywords: HQChart HQChartPy2
Platform: UNKNOWN
Classifier: Operating System :: Microsoft :: Windows
